nbhub.py
nbhub-20.4a0.dist-info/LICENSE.txt
nbhub-20.4a0.dist-info/METADATA
nbhub-20.4a0.dist-info/WHEEL
nbhub-20.4a0.dist-info/entry_points.txt
nbhub-20.4a0.dist-info/top_level.txt
nbhub-20.4a0.dist-info/RECORD
