Metadata-Version: 2.1
Name: nbhub
Version: 20.4a0
Summary: Publish jupyter notebooks from the command line.
Home-page: https://github.com/duarteocarmo/nbhub
Author: Duarte O.Carmo
Author-email: duarteocarmo@gmail.com
License: UNKNOWN
Project-URL: Bug Reports, https://github.com/duarteocarmo/nbhub/issues
Project-URL: Say Thanks!, https://nbhub.duarteocarmo.com
Project-URL: Source, https://github.com/duarteocarmo/nbhub
Keywords: jupyter notebook cli sharing
Platform: UNKNOWN
Classifier: Development Status :: 3 - Alpha
Classifier: Environment :: Console
Classifier: Intended Audience :: Developers
Classifier: Intended Audience :: Education
Classifier: Intended Audience :: Science/Research
Classifier: License :: OSI Approved :: GNU General Public License v3 (GPLv3)
Classifier: Programming Language :: Python
Classifier: Programming Language :: Python :: 3
Classifier: Programming Language :: Python :: 3.6
Classifier: Programming Language :: Python :: 3.7
Classifier: Programming Language :: Python :: 3.8
Classifier: Programming Language :: Python :: 3 :: Only
Classifier: Topic :: Utilities
Requires-Python: >=3.6
Requires-Dist: click
Requires-Dist: requests
Provides-Extra: test
Requires-Dist: coverage ; extra == 'test'
Requires-Dist: pytest ; extra == 'test'
